{"frames":{"char_honoka_idle_f1":{"frame":{"x":0,"y":0,"w":720,"h":720},"rotated":false,"trimmed":false,"spriteSourceSize":{"x":0,"y":0,"w":720,"h":720},"sourceSize":{"w":720,"h":720}},"char_honoka_idle_f2":{"frame":{"x":720,"y":0,"w":720,"h":720},"rotated":false,"trimmed":false,"spriteSourceSize":{"x":0,"y":0,"w":720,"h":720},"sourceSize":{"w":720,"h":720}},"char_honoka_idle_f3":{"frame":{"x":1440,"y":0,"w":720,"h":720},"rotated":false,"trimmed":false,"spriteSourceSize":{"x":0,"y":0,"w":720,"h":720},"sourceSize":{"w":720,"h":720}},"char_honoka_idle_f4":{"frame":{"x":2160,"y":0,"w":720,"h":720},"rotated":false,"trimmed":false,"spriteSourceSize":{"x":0,"y":0,"w":720,"h":720},"sourceSize":{"w":720,"h":720}},"char_honoka_lean_left_f1":{"frame":{"x":2880,"y":0,"w":720,"h":720},"rotated":false,"trimmed":false,"spriteSourceSize":{"x":0,"y":0,"w":720,"h":720},"sourceSize":{"w":720,"h":720}},"char_honoka_lean_left_f2":{"frame":{"x":0,"y":720,"w":720,"h":720},"rotated":false,"trimmed":false,"spriteSourceSize":{"x":0,"y":0,"w":720,"h":720},"sourceSize":{"w":720,"h":720}},"char_honoka_forward_f1":{"frame":{"x":720,"y":720,"w":720,"h":720},"rotated":false,"trimmed":false,"spriteSourceSize":{"x":0,"y":0,"w":720,"h":720},"sourceSize":{"w":720,"h":720}},"char_honoka_forward_f2":{"frame":{"x":1440,"y":720,"w":720,"h":720},"rotated":false,"trimmed":false,"spriteSourceSize":{"x":0,"y":0,"w":720,"h":720},"sourceSize":{"w":720,"h":720}},"char_honoka_hit_f1":{"frame":{"x":2160,"y":720,"w":720,"h":720},"rotated":false,"trimmed":false,"spriteSourceSize":{"x":0,"y":0,"w":720,"h":720},"sourceSize":{"w":720,"h":720}},"char_honoka_death_f1":{"frame":{"x":2880,"y":720,"w":720,"h":720},"rotated":false,"trimmed":false,"spriteSourceSize":{"x":0,"y":0,"w":720,"h":720},"sourceSize":{"w":720,"h":720}},"char_honoka_death_f2":{"frame":{"x":0,"y":1440,"w":720,"h":720},"rotated":false,"trimmed":false,"spriteSourceSize":{"x":0,"y":0,"w":720,"h":720},"sourceSize":{"w":720,"h":720}},"char_honoka_death_f3":{"frame":{"x":720,"y":1440,"w":720,"h":720},"rotated":false,"trimmed":false,"spriteSourceSize":{"x":0,"y":0,"w":720,"h":720},"sourceSize":{"w":720,"h":720}},"char_honoka_collect_f1":{"frame":{"x":1440,"y":1440,"w":720,"h":720},"rotated":false,"trimmed":false,"spriteSourceSize":{"x":0,"y":0,"w":720,"h":720},"sourceSize":{"w":720,"h":720}},"char_honoka_home_idle":{"frame":{"x":2160,"y":1440,"w":538,"h":720},"rotated":false,"trimmed":false,"spriteSourceSize":{"x":0,"y":0,"w":538,"h":720},"sourceSize":{"w":538,"h":720}},"char_honoka_home_jump":{"frame":{"x":2698,"y":1440,"w":538,"h":720},"rotated":false,"trimmed":false,"spriteSourceSize":{"x":0,"y":0,"w":538,"h":720},"sourceSize":{"w":538,"h":720}},"char_honoka_gameover":{"frame":{"x":3236,"y":1440,"w":720,"h":720},"rotated":false,"trimmed":false,"spriteSourceSize":{"x":0,"y":0,"w":720,"h":720},"sourceSize":{"w":720,"h":720}},"char_honoka_surfboard":{"frame":{"x":0,"y":2160,"w":538,"h":720},"rotated":false,"trimmed":false,"spriteSourceSize":{"x":0,"y":0,"w":538,"h":720},"sourceSize":{"w":538,"h":720}},"char_honoka_portrait":{"frame":{"x":538,"y":2160,"w":720,"h":720},"rotated":false,"trimmed":false,"spriteSourceSize":{"x":0,"y":0,"w":720,"h":720},"sourceSize":{"w":720,"h":720}}},"meta":{"app":"pack-assets.mjs","version":"1.0","image":"char_honoka.webp","format":"RGBA8888","size":{"w":3956,"h":2880},"scale":"1"}}